[{"ID":"00001","Nombre":"Consumidor","Contacto":"NA","Identificacion":222222222},{"ID":"00003","Nombre":"Ana Banana","Contacto":"12794992386","Identificacion":125648913},{"ID":"00004","Nombre":"Jamison Young","Contacto":"13479466861","Identificacion":12110613},{"ID":"00005","Nombre":"Waylon Perkins","Contacto":"uxe32954@zslsz.com","Identificacion":19170796},{"ID":"00006","Nombre":"Jada Jennings","Contacto":"16059719337","Identificacion":13746291},{"ID":"00007","Nombre":"Beverly Keith","Contacto":"ybc81691@zbock.com","Identificacion":1500440},{"ID":"00008","Nombre":"Madelynn Morrison","Contacto":"474789468","Identificacion":18803899},{"ID":"00009","Nombre":"Madelynn Morrison","Contacto":"rwo60296@nezid.com","Identificacion":2596763}]